dnns/__init__.py
dnns/config.py
dnns/data.py
dnns/loader.py
dnns/models.py
dnns-1.4.7.data/scripts/lossPlot.py
dnns-1.4.7.data/scripts/splitDataset.py
dnns-1.4.7.data/scripts/tvpPlot.py
dnns-1.4.7.data/scripts/worker.py
dnns-1.4.7.dist-info/LICENSE
dnns-1.4.7.dist-info/METADATA
dnns-1.4.7.dist-info/WHEEL
dnns-1.4.7.dist-info/top_level.txt
dnns-1.4.7.dist-info/RECORD
