Metadata-Version: 2.1
Name: dnns
Version: 1.4.7
Summary: A deep learning package for using HDF5 and Pytorch (Distributed Data Parallel with NVIDIA mixed-precision) with ease.
Home-page: https://github.com/CLEANit/dnns.git
Author: Kevin Ryczko
Author-email: kevin.ryczko@uottawa.ca
License: UNKNOWN
Platform: UNKNOWN
Classifier: Programming Language :: Python :: 3
Classifier: Operating System :: OS Independent
Requires-Dist: torch
